stmdency/__init__.py
stmdency/constants.py
stmdency/extractor.py
stmdency/models/__init__.py
stmdency/models/node.py
stmdency/visitors/__init__.py
stmdency/visitors/assign.py
stmdency/visitors/base.py
stmdency/visitors/function_def.py
stmdency-0.0.5.dist-info/METADATA
stmdency-0.0.5.dist-info/WHEEL
stmdency-0.0.5.dist-info/top_level.txt
stmdency-0.0.5.dist-info/zip-safe
stmdency-0.0.5.dist-info/RECORD
