Metadata-Version: 2.1
Name: stmdency
Version: 0.0.5
Summary: A library extracting dependencies between statements in Python program.
Home-page: https://github.com/zhongjiajie/stmdency
Author: Jay Chung
Author-email: zhongjiajie955@gmail.com
License: Apache License 2.0
Project-URL: Source, https://github.com/zhongjiajie/stmdency
Project-URL: Issue Tracker, https://github.com/zhongjiajie/stmdency/issues
Project-URL: Documentation, https://stmdency.readthedocs.io
Project-URL: Changelog, https://github.com/zhongjiajie/stmdency/releases
Keywords: all
Classifier: Development Status :: 3 - Alpha
Classifier: License :: OSI Approved :: Apache Software License
Classifier: Operating System :: OS Independent
Classifier: Programming Language :: Python
Classifier: Programming Language :: Python :: 3
Classifier: Programming Language :: Python :: 3 :: Only
Classifier: Programming Language :: Python :: 3.7
Classifier: Programming Language :: Python :: 3.8
Classifier: Programming Language :: Python :: 3.9
Classifier: Programming Language :: Python :: 3.10
Classifier: Programming Language :: Python :: 3.11
Classifier: Programming Language :: Python :: 3.12
Classifier: Programming Language :: Python :: Implementation :: CPython
Classifier: Environment :: Console
Classifier: Topic :: Software Development :: Libraries :: Python Modules
Requires-Python: >=3.7
Requires-Dist: libcst
Provides-Extra: dev
Requires-Dist: black >=22.8 ; extra == 'dev'
Requires-Dist: flake8 >=4.0 ; extra == 'dev'
Requires-Dist: flake8-docstrings >=1.6 ; extra == 'dev'
Requires-Dist: flake8-black >=0.2 ; extra == 'dev'
Requires-Dist: isort >=5.10 ; extra == 'dev'
Requires-Dist: autoflake >=1.4 ; extra == 'dev'
Requires-Dist: pytest >=6.2 ; extra == 'dev'
Requires-Dist: pytest-cov >=3.0 ; extra == 'dev'
Requires-Dist: sphinx >=4.3 ; extra == 'dev'
Requires-Dist: sphinx-rtd-theme >=1.0 ; extra == 'dev'
Requires-Dist: sphinx-copybutton >=0.4.0 ; extra == 'dev'
Requires-Dist: sphinx-argparse >=0.3.2 ; extra == 'dev'
